{"cameraMode":{"drawMode":0,"name":"Shaded","section":"Shading Mode"},"sceneLighting":true,"audioPlay":false,"sceneViewState":{"m_AlwaysRefresh":false,"showFog":true,"showSkybox":true,"showFlares":true,"showImageEffects":true,"showParticleSystems":true,"showVisualEffectGraphs":true,"m_FxEnabled":true},"in2DMode":false,"pivot":{"x":0.0,"y":0.9190130233764648,"z":0.0},"rotation":{"x":0.23884522914886475,"y":-0.48295634984970095,"z":0.13882328569889069,"w":0.8309288620948792},"size":10.0,"orthographic":false}